backoff/__init__.py
another_exponential_backoff-1.0.0.dist-info/METADATA
another_exponential_backoff-1.0.0.dist-info/WHEEL
another_exponential_backoff-1.0.0.dist-info/top_level.txt
another_exponential_backoff-1.0.0.dist-info/RECORD
