Metadata-Version: 2.1
Name: another-exponential-backoff
Version: 1.0.0
Summary: Simple exponential backoff script
Home-page: https://github.com/dragdev-studios/exponential-backoff-python
Author: EEKIM10
Author-email: eek@clicksminuteper.net
License: MIT
Project-URL: Issue Tracker, https://github.com/dragdev-studios/exponential-backoff-python
Project-URL: Repository, https://github.com/dragdev-studios/exponential-backoff-python
Platform: UNKNOWN
Requires-Python: >=3.6
Provides-Extra: tests
Requires-Dist: pytest ; extra == 'tests'
